{
  "timestamp": "2026-05-10T02:00:18.962904",
  "model": "RF+XGB 앙상블 Optuna튜닝 (시간대별 독립)",
  "model_version": "v5",
  "optuna_trials": 30,
  "params_cached": true,
  "features_used": [
    "emd_enc",
    "month",
    "temp",
    "humidity",
    "wind_speed",
    "hist_count",
    "hist_area",
    "hist_score",
    "month_fire_score",
    "month_high_ratio"
  ],
  "thresholds": {
    "overall_high": 0.2714,
    "overall_medium": 0.1628,
    "AM": {
      "high": 0.2507,
      "medium": 0.1504
    },
    "PM": {
      "high": 0.3019,
      "medium": 0.1811
    },
    "NIGHT": {
      "high": 0.2261,
      "medium": 0.1357
    }
  },
  "threshold_high_am": 0.2507,
  "threshold_high_pm": 0.3019,
  "threshold_high_night": 0.2261,
  "threshold_medium_am": 0.1504,
  "threshold_medium_pm": 0.1811,
  "threshold_medium_night": 0.1357,
  "threshold_reason": {
    "AM": "Youden Index (TPR-FPR 최대화) 기반 자동 도출 (J=0.488, AM)",
    "PM": "Youden Index (TPR-FPR 최대화) 기반 자동 도출 (J=0.502, PM)",
    "NIGHT": "Youden Index (TPR-FPR 최대화) 기반 자동 도출 (J=0.504, NIGHT)"
  },
  "period_weights": {
    "AM": 0.3,
    "PM": 0.5,
    "NIGHT": 0.2
  },
  "period_models": {
    "AM": {
      "rf_auc": 0.8001,
      "xgb_auc": 0.6881,
      "ens_auc": 0.7847,
      "cv_mean": 0.6966,
      "cv_std": 0.0962,
      "rf_weight": 0.8956988267099524,
      "best_params": {
        "rf_n_estimators": 500,
        "rf_max_depth": 4,
        "rf_min_samples_leaf": 9,
        "rf_min_samples_split": 32,
        "xgb_n_estimators": 200,
        "xgb_max_depth": 6,
        "xgb_learning_rate": 0.07553862533210692,
        "xgb_min_child_weight": 4,
        "rf_weight": 0.8956988267099524
      }
    },
    "PM": {
      "rf_auc": 0.8017,
      "xgb_auc": 0.6498,
      "ens_auc": 0.7841,
      "cv_mean": 0.6983,
      "cv_std": 0.0956,
      "rf_weight": 0.8450041603152055,
      "best_params": {
        "rf_n_estimators": 450,
        "rf_max_depth": 4,
        "rf_min_samples_leaf": 10,
        "rf_min_samples_split": 25,
        "xgb_n_estimators": 400,
        "xgb_max_depth": 7,
        "xgb_learning_rate": 0.07759302594525883,
        "xgb_min_child_weight": 6,
        "rf_weight": 0.8450041603152055
      }
    },
    "NIGHT": {
      "rf_auc": 0.7935,
      "xgb_auc": 0.7901,
      "ens_auc": 0.7923,
      "cv_mean": 0.6709,
      "cv_std": 0.1023,
      "rf_weight": 0.43094229751332164,
      "best_params": {
        "rf_n_estimators": 400,
        "rf_max_depth": 5,
        "rf_min_samples_leaf": 8,
        "rf_min_samples_split": 27,
        "xgb_n_estimators": 250,
        "xgb_max_depth": 4,
        "xgb_learning_rate": 0.010348283943495601,
        "xgb_min_child_weight": 10,
        "rf_weight": 0.43094229751332164
      }
    }
  },
  "weather_condition": {
    "temperature": 22.8,
    "humidity": 40,
    "wind_speed": 2.0,
    "month": 5
  },
  "forest_danger_grade": 3,
  "forest_overall_label": "높음",
  "summary": {
    "total_dongs": 81,
    "high_risk": 13,
    "medium_risk": 68,
    "low_risk": 0,
    "high_risk_am": 24,
    "high_risk_pm": 10,
    "high_risk_night": 48
  },
  "predictions": [
    {
      "dong": "전곡",
      "myeon": "서신",
      "lat": 37.1671,
      "lng": 126.6119,
      "probability": 0.476,
      "level": "HIGH",
      "prob_am": 0.503,
      "prob_pm": 0.424,
      "prob_night": 0.563,
      "level_am": "HIGH",
      "level_pm": "HIGH",
      "level_night": "HIGH",
      "hist_count": 4,
      "hist_score": 0.56,
      "top_cause": "쓰레기소각",
      "forest_danger_grade": 3
    },
    {
      "dong": "백미",
      "myeon": "서신",
      "lat": 37.1686,
      "lng": 126.5971,
      "probability": 0.455,
      "level": "HIGH",
      "prob_am": 0.477,
      "prob_pm": 0.413,
      "prob_night": 0.527,
      "level_am": "HIGH",
      "level_pm": "HIGH",
      "level_night": "HIGH",
      "hist_count": 4,
      "hist_score": 0.536,
      "top_cause": "쓰레기소각",
      "forest_danger_grade": 3
    },
    {
      "dong": "송림",
      "myeon": "남양",
      "lat": 37.2224,
      "lng": 126.7282,
      "probability": 0.451,
      "level": "HIGH",
      "prob_am": 0.459,
      "prob_pm": 0.417,
      "prob_night": 0.526,
      "level_am": "HIGH",
      "level_pm": "HIGH",
      "level_night": "HIGH",
      "hist_count": 4,
      "hist_score": 0.517,
      "top_cause": "쓰레기소각",
      "forest_danger_grade": 3
    },
    {
      "dong": "용두",
      "myeon": "서신",
      "lat": 37.164,
      "lng": 126.6101,
      "probability": 0.414,
      "level": "HIGH",
      "prob_am": 0.416,
      "prob_pm": 0.4,
      "prob_night": 0.448,
      "level_am": "HIGH",
      "level_pm": "HIGH",
      "level_night": "HIGH",
      "hist_count": 5,
      "hist_score": 0.686,
      "top_cause": "쓰레기소각",
      "forest_danger_grade": 3
    },
    {
      "dong": "원평",
      "myeon": "매송",
      "lat": 37.1996,
      "lng": 126.8312,
      "probability": 0.326,
      "level": "HIGH",
      "prob_am": 0.283,
      "prob_pm": 0.316,
      "prob_night": 0.412,
      "level_am": "HIGH",
      "level_pm": "HIGH",
      "level_night": "HIGH",
      "hist_count": 2,
      "hist_score": 0.299,
      "top_cause": "입산자실화",
      "forest_danger_grade": 3
    },
    {
      "dong": "중",
      "myeon": "",
      "lat": 37.1996,
      "lng": 126.8312,
      "probability": 0.323,
      "level": "HIGH",
      "prob_am": 0.289,
      "prob_pm": 0.307,
      "prob_night": 0.411,
      "level_am": "HIGH",
      "level_pm": "HIGH",
      "level_night": "HIGH",
      "hist_count": 2,
      "hist_score": 0.291,
      "top_cause": "담뱃불실화",
      "forest_danger_grade": 3
    },
    {
      "dong": "자안",
      "myeon": "비봉",
      "lat": 37.2439,
      "lng": 126.8153,
      "probability": 0.321,
      "level": "HIGH",
      "prob_am": 0.287,
      "prob_pm": 0.304,
      "prob_night": 0.415,
      "level_am": "HIGH",
      "level_pm": "HIGH",
      "level_night": "HIGH",
      "hist_count": 2,
      "hist_score": 0.291,
      "top_cause": "담뱃불실화",
      "forest_danger_grade": 3
    },
    {
      "dong": "중송",
      "myeon": "송산",
      "lat": 37.2091,
      "lng": 126.6876,
      "probability": 0.314,
      "level": "HIGH",
      "prob_am": 0.281,
      "prob_pm": 0.303,
      "prob_night": 0.39,
      "level_am": "HIGH",
      "level_pm": "HIGH",
      "level_night": "HIGH",
      "hist_count": 2,
      "hist_score": 0.309,
      "top_cause": "기타",
      "forest_danger_grade": 3
    },
    {
      "dong": "야목",
      "myeon": "매송",
      "lat": 37.1996,
      "lng": 126.8312,
      "probability": 0.308,
      "level": "HIGH",
      "prob_am": 0.292,
      "prob_pm": 0.309,
      "prob_night": 0.33,
      "level_am": "HIGH",
      "level_pm": "HIGH",
      "level_night": "HIGH",
      "hist_count": 3,
      "hist_score": 0.419,
      "top_cause": "기타",
      "forest_danger_grade": 3
    },
    {
      "dong": "지화",
      "myeon": "송산",
      "lat": 37.1917,
      "lng": 126.6979,
      "probability": 0.306,
      "level": "HIGH",
      "prob_am": 0.299,
      "prob_pm": 0.316,
      "prob_night": 0.293,
      "level_am": "HIGH",
      "level_pm": "HIGH",
      "level_night": "HIGH",
      "hist_count": 3,
      "hist_score": 0.414,
      "top_cause": "쓰레기소각",
      "forest_danger_grade": 3
    },
    {
      "dong": "어은",
      "myeon": "장안",
      "lat": 37.0455,
      "lng": 126.7677,
      "probability": 0.293,
      "level": "HIGH",
      "prob_am": 0.278,
      "prob_pm": 0.282,
      "prob_night": 0.341,
      "level_am": "HIGH",
      "level_pm": "MEDIUM",
      "level_night": "HIGH",
      "hist_count": 3,
      "hist_score": 0.388,
      "top_cause": "농산부산물소각",
      "forest_danger_grade": 3
    },
    {
      "dong": "내",
      "myeon": "봉담",
      "lat": 37.2176,
      "lng": 126.9295,
      "probability": 0.288,
      "level": "HIGH",
      "prob_am": 0.292,
      "prob_pm": 0.279,
      "prob_night": 0.302,
      "level_am": "HIGH",
      "level_pm": "MEDIUM",
      "level_night": "HIGH",
      "hist_count": 3,
      "hist_score": 0.413,
      "top_cause": "기타",
      "forest_danger_grade": 3
    },
    {
      "dong": "백곡",
      "myeon": "마도",
      "lat": 37.1462,
      "lng": 126.71,
      "probability": 0.28,
      "level": "HIGH",
      "prob_am": 0.272,
      "prob_pm": 0.274,
      "prob_night": 0.309,
      "level_am": "HIGH",
      "level_pm": "MEDIUM",
      "level_night": "HIGH",
      "hist_count": 3,
      "hist_score": 0.467,
      "top_cause": "쓰레기소각",
      "forest_danger_grade": 3
    },
    {
      "dong": "문호",
      "myeon": "남양",
      "lat": 37.1914,
      "lng": 126.7286,
      "probability": 0.268,
      "level": "MEDIUM",
      "prob_am": 0.276,
      "prob_pm": 0.281,
      "prob_night": 0.225,
      "level_am": "HIGH",
      "level_pm": "MEDIUM",
      "level_night": "MEDIUM",
      "hist_count": 2,
      "hist_score": 0.64,
      "top_cause": "쓰레기소각",
      "forest_danger_grade": 3
    },
    {
      "dong": "송라",
      "myeon": "매송",
      "lat": 37.1996,
      "lng": 126.8312,
      "probability": 0.265,
      "level": "MEDIUM",
      "prob_am": 0.251,
      "prob_pm": 0.257,
      "prob_night": 0.308,
      "level_am": "MEDIUM",
      "level_pm": "MEDIUM",
      "level_night": "HIGH",
      "hist_count": 2,
      "hist_score": 0.306,
      "top_cause": "쓰레기소각",
      "forest_danger_grade": 3
    },
    {
      "dong": "독지",
      "myeon": "송산",
      "lat": 37.1845,
      "lng": 126.6829,
      "probability": 0.262,
      "level": "MEDIUM",
      "prob_am": 0.259,
      "prob_pm": 0.251,
      "prob_night": 0.291,
      "level_am": "HIGH",
      "level_pm": "MEDIUM",
      "level_night": "HIGH",
      "hist_count": 3,
      "hist_score": 0.388,
      "top_cause": "기타",
      "forest_danger_grade": 3
    },
    {
      "dong": "해문",
      "myeon": "마도",
      "lat": 37.1154,
      "lng": 126.719,
      "probability": 0.261,
      "level": "MEDIUM",
      "prob_am": 0.276,
      "prob_pm": 0.271,
      "prob_night": 0.212,
      "level_am": "HIGH",
      "level_pm": "MEDIUM",
      "level_night": "MEDIUM",
      "hist_count": 3,
      "hist_score": 0.375,
      "top_cause": "농산부산물소각",
      "forest_danger_grade": 3
    },
    {
      "dong": "쌍송",
      "myeon": "마도",
      "lat": 37.128,
      "lng": 126.7006,
      "probability": 0.259,
      "level": "MEDIUM",
      "prob_am": 0.25,
      "prob_pm": 0.261,
      "prob_night": 0.266,
      "level_am": "MEDIUM",
      "level_pm": "MEDIUM",
      "level_night": "HIGH",
      "hist_count": 2,
      "hist_score": 0.382,
      "top_cause": "쓰레기소각",
      "forest_danger_grade": 3
    },
    {
      "dong": "관항",
      "myeon": "정남",
      "lat": 37.1598,
      "lng": 127.0055,
      "probability": 0.255,
      "level": "MEDIUM",
      "prob_am": 0.251,
      "prob_pm": 0.248,
      "prob_night": 0.277,
      "level_am": "HIGH",
      "level_pm": "MEDIUM",
      "level_night": "HIGH",
      "hist_count": 2,
      "hist_score": 0.302,
      "top_cause": "농산부산물소각",
      "forest_danger_grade": 3
    },
    {
      "dong": "상기",
      "myeon": "봉담",
      "lat": 37.2145,
      "lng": 126.9063,
      "probability": 0.255,
      "level": "MEDIUM",
      "prob_am": 0.241,
      "prob_pm": 0.251,
      "prob_night": 0.285,
      "level_am": "MEDIUM",
      "level_pm": "MEDIUM",
      "level_night": "HIGH",
      "hist_count": 2,
      "hist_score": 0.32,
      "top_cause": "쓰레기소각",
      "forest_danger_grade": 3
    },
    {
      "dong": "백",
      "myeon": "정남",
      "lat": 37.1321,
      "lng": 127.0199,
      "probability": 0.254,
      "level": "MEDIUM",
      "prob_am": 0.242,
      "prob_pm": 0.244,
      "prob_night": 0.296,
      "level_am": "MEDIUM",
      "level_pm": "MEDIUM",
      "level_night": "HIGH",
      "hist_count": 2,
      "hist_score": 0.314,
      "top_cause": "쓰레기소각",
      "forest_danger_grade": 3
    },
    {
      "dong": "길성",
      "myeon": "향남",
      "lat": 37.0668,
      "lng": 126.8332,
      "probability": 0.253,
      "level": "MEDIUM",
      "prob_am": 0.274,
      "prob_pm": 0.247,
      "prob_night": 0.238,
      "level_am": "HIGH",
      "level_pm": "MEDIUM",
      "level_night": "HIGH",
      "hist_count": 3,
      "hist_score": 0.371,
      "top_cause": "농산부산물소각",
      "forest_danger_grade": 3
    },
    {
      "dong": "궁평",
      "myeon": "서신",
      "lat": 37.1644,
      "lng": 126.6074,
      "probability": 0.25,
      "level": "MEDIUM",
      "prob_am": 0.289,
      "prob_pm": 0.216,
      "prob_night": 0.278,
      "level_am": "HIGH",
      "level_pm": "MEDIUM",
      "level_night": "HIGH",
      "hist_count": 1,
      "hist_score": 0.122,
      "top_cause": "쓰레기소각",
      "forest_danger_grade": 3
    },
    {
      "dong": "시",
      "myeon": "남양",
      "lat": 37.2013,
      "lng": 126.7267,
      "probability": 0.25,
      "level": "MEDIUM",
      "prob_am": 0.245,
      "prob_pm": 0.263,
      "prob_night": 0.226,
      "level_am": "MEDIUM",
      "level_pm": "MEDIUM",
      "level_night": "MEDIUM",
      "hist_count": 2,
      "hist_score": 0.408,
      "top_cause": "쓰레기소각",
      "forest_danger_grade": 3
    },
    {
      "dong": "창곡",
      "myeon": "팔탄",
      "lat": 37.086,
      "lng": 126.8688,
      "probability": 0.25,
      "level": "MEDIUM",
      "prob_am": 0.269,
      "prob_pm": 0.26,
      "prob_night": 0.196,
      "level_am": "HIGH",
      "level_pm": "MEDIUM",
      "level_night": "MEDIUM",
      "hist_count": 3,
      "hist_score": 0.366,
      "top_cause": "쓰레기소각",
      "forest_danger_grade": 3
    },
    {
      "dong": "신남",
      "myeon": "남양",
      "lat": 37.2175,
      "lng": 126.726,
      "probability": 0.246,
      "level": "MEDIUM",
      "prob_am": 0.241,
      "prob_pm": 0.251,
      "prob_night": 0.241,
      "level_am": "MEDIUM",
      "level_pm": "MEDIUM",
      "level_night": "HIGH",
      "hist_count": 2,
      "hist_score": 0.362,
      "top_cause": "농산부산물소각",
      "forest_danger_grade": 3
    },
    {
      "dong": "석포",
      "myeon": "장안",
      "lat": 37.0389,
      "lng": 126.7837,
      "probability": 0.244,
      "level": "MEDIUM",
      "prob_am": 0.241,
      "prob_pm": 0.249,
      "prob_night": 0.237,
      "level_am": "MEDIUM",
      "level_pm": "MEDIUM",
      "level_night": "HIGH",
      "hist_count": 2,
      "hist_score": 0.39,
      "top_cause": "농산부산물소각",
      "forest_danger_grade": 3
    },
    {
      "dong": "신천",
      "myeon": "송산",
      "lat": 37.2027,
      "lng": 126.705,
      "probability": 0.244,
      "level": "MEDIUM",
      "prob_am": 0.239,
      "prob_pm": 0.239,
      "prob_night": 0.264,
      "level_am": "MEDIUM",
      "level_pm": "MEDIUM",
      "level_night": "HIGH",
      "hist_count": 2,
      "hist_score": 0.255,
      "top_cause": "입산자실화",
      "forest_danger_grade": 3
    },
    {
      "dong": "상안",
      "myeon": "서신",
      "lat": 37.1778,
      "lng": 126.5903,
      "probability": 0.242,
      "level": "MEDIUM",
      "prob_am": 0.236,
      "prob_pm": 0.245,
      "prob_night": 0.243,
      "level_am": "MEDIUM",
      "level_pm": "MEDIUM",
      "level_night": "HIGH",
      "hist_count": 2,
      "hist_score": 0.359,
      "top_cause": "쓰레기소각",
      "forest_danger_grade": 3
    },
    {
      "dong": "숙곡",
      "myeon": "매송",
      "lat": 37.1996,
      "lng": 126.8312,
      "probability": 0.239,
      "level": "MEDIUM",
      "prob_am": 0.236,
      "prob_pm": 0.234,
      "prob_night": 0.256,
      "level_am": "MEDIUM",
      "level_pm": "MEDIUM",
      "level_night": "HIGH",
      "hist_count": 2,
      "hist_score": 0.276,
      "top_cause": "농산부산물소각",
      "forest_danger_grade": 3
    },
    {
      "dong": "유포",
      "myeon": "비봉",
      "lat": 37.2586,
      "lng": 126.7804,
      "probability": 0.233,
      "level": "MEDIUM",
      "prob_am": 0.26,
      "prob_pm": 0.208,
      "prob_night": 0.252,
      "level_am": "HIGH",
      "level_pm": "MEDIUM",
      "level_night": "HIGH",
      "hist_count": 1,
      "hist_score": 0.122,
      "top_cause": "쓰레기소각",
      "forest_danger_grade": 3
    },
    {
      "dong": "노하",
      "myeon": "팔탄",
      "lat": 37.0993,
      "lng": 126.8928,
      "probability": 0.232,
      "level": "MEDIUM",
      "prob_am": 0.244,
      "prob_pm": 0.225,
      "prob_night": 0.231,
      "level_am": "MEDIUM",
      "level_pm": "MEDIUM",
      "level_night": "HIGH",
      "hist_count": 2,
      "hist_score": 0.251,
      "top_cause": "기타",
      "forest_danger_grade": 3
    },
    {
      "dong": "홍법",
      "myeon": "서신",
      "lat": 37.1918,
      "lng": 126.5945,
      "probability": 0.232,
      "level": "MEDIUM",
      "prob_am": 0.23,
      "prob_pm": 0.237,
      "prob_night": 0.222,
      "level_am": "MEDIUM",
      "level_pm": "MEDIUM",
      "level_night": "MEDIUM",
      "hist_count": 2,
      "hist_score": 0.265,
      "top_cause": "농산부산물소각",
      "forest_danger_grade": 3
    },
    {
      "dong": "장짐",
      "myeon": "향남",
      "lat": 37.074,
      "lng": 126.8198,
      "probability": 0.231,
      "level": "MEDIUM",
      "prob_am": 0.253,
      "prob_pm": 0.209,
      "prob_night": 0.253,
      "level_am": "HIGH",
      "level_pm": "MEDIUM",
      "level_night": "HIGH",
      "hist_count": 1,
      "hist_score": 0.122,
      "top_cause": "입산자실화",
      "forest_danger_grade": 3
    },
    {
      "dong": "제기",
      "myeon": "정남",
      "lat": 37.1527,
      "lng": 127.0197,
      "probability": 0.231,
      "level": "MEDIUM",
      "prob_am": 0.254,
      "prob_pm": 0.209,
      "prob_night": 0.25,
      "level_am": "HIGH",
      "level_pm": "MEDIUM",
      "level_night": "HIGH",
      "hist_count": 1,
      "hist_score": 0.122,
      "top_cause": "쓰레기소각",
      "forest_danger_grade": 3
    },
    {
      "dong": "남양",
      "myeon": "남양",
      "lat": 37.2157,
      "lng": 126.7383,
      "probability": 0.23,
      "level": "MEDIUM",
      "prob_am": 0.235,
      "prob_pm": 0.226,
      "prob_night": 0.233,
      "level_am": "MEDIUM",
      "level_pm": "MEDIUM",
      "level_night": "HIGH",
      "hist_count": 2,
      "hist_score": 0.269,
      "top_cause": "담뱃불실화",
      "forest_danger_grade": 3
    },
    {
      "dong": "제부",
      "myeon": "서신",
      "lat": 37.1945,
      "lng": 126.5982,
      "probability": 0.227,
      "level": "MEDIUM",
      "prob_am": 0.224,
      "prob_pm": 0.215,
      "prob_night": 0.261,
      "level_am": "MEDIUM",
      "level_pm": "MEDIUM",
      "level_night": "HIGH",
      "hist_count": 1,
      "hist_score": 0.166,
      "top_cause": "쓰레기소각",
      "forest_danger_grade": 3
    },
    {
      "dong": "괘랑",
      "myeon": "정남",
      "lat": 37.1397,
      "lng": 127.0066,
      "probability": 0.226,
      "level": "MEDIUM",
      "prob_am": 0.25,
      "prob_pm": 0.204,
      "prob_night": 0.245,
      "level_am": "MEDIUM",
      "level_pm": "MEDIUM",
      "level_night": "HIGH",
      "hist_count": 1,
      "hist_score": 0.128,
      "top_cause": "기타",
      "forest_danger_grade": 3
    },
    {
      "dong": "광평",
      "myeon": "서신",
      "lat": 37.1808,
      "lng": 126.6083,
      "probability": 0.225,
      "level": "MEDIUM",
      "prob_am": 0.252,
      "prob_pm": 0.202,
      "prob_night": 0.243,
      "level_am": "HIGH",
      "level_pm": "MEDIUM",
      "level_night": "HIGH",
      "hist_count": 1,
      "hist_score": 0.125,
      "top_cause": "쓰레기소각",
      "forest_danger_grade": 3
    },
    {
      "dong": "기천",
      "myeon": "팔탄",
      "lat": 37.088,
      "lng": 126.8766,
      "probability": 0.225,
      "level": "MEDIUM",
      "prob_am": 0.249,
      "prob_pm": 0.201,
      "prob_night": 0.247,
      "level_am": "MEDIUM",
      "level_pm": "MEDIUM",
      "level_night": "HIGH",
      "hist_count": 1,
      "hist_score": 0.129,
      "top_cause": "기타",
      "forest_danger_grade": 3
    },
    {
      "dong": "삼화",
      "myeon": "비봉",
      "lat": 37.2456,
      "lng": 126.8124,
      "probability": 0.225,
      "level": "MEDIUM",
      "prob_am": 0.223,
      "prob_pm": 0.223,
      "prob_night": 0.234,
      "level_am": "MEDIUM",
      "level_pm": "MEDIUM",
      "level_night": "HIGH",
      "hist_count": 2,
      "hist_score": 0.266,
      "top_cause": "건축물화재비화",
      "forest_danger_grade": 3
    },
    {
      "dong": "장안",
      "myeon": "장안",
      "lat": 37.0504,
      "lng": 126.7802,
      "probability": 0.225,
      "level": "MEDIUM",
      "prob_am": 0.226,
      "prob_pm": 0.211,
      "prob_night": 0.259,
      "level_am": "MEDIUM",
      "level_pm": "MEDIUM",
      "level_night": "HIGH",
      "hist_count": 1,
      "hist_score": 0.166,
      "top_cause": "농산부산물소각",
      "forest_danger_grade": 3
    },
    {
      "dong": "덕천",
      "myeon": "팔탄",
      "lat": 37.0979,
      "lng": 126.888,
      "probability": 0.223,
      "level": "MEDIUM",
      "prob_am": 0.226,
      "prob_pm": 0.228,
      "prob_night": 0.207,
      "level_am": "MEDIUM",
      "level_pm": "MEDIUM",
      "level_night": "MEDIUM",
      "hist_count": 2,
      "hist_score": 0.331,
      "top_cause": "농산부산물소각",
      "forest_danger_grade": 3
    },
    {
      "dong": "무송",
      "myeon": "남양",
      "lat": 37.2174,
      "lng": 126.7389,
      "probability": 0.219,
      "level": "MEDIUM",
      "prob_am": 0.223,
      "prob_pm": 0.212,
      "prob_night": 0.228,
      "level_am": "MEDIUM",
      "level_pm": "MEDIUM",
      "level_night": "HIGH",
      "hist_count": 2,
      "hist_score": 0.254,
      "top_cause": "담뱃불실화",
      "forest_danger_grade": 3
    },
    {
      "dong": "신왕",
      "myeon": "양감",
      "lat": 37.006,
      "lng": 126.882,
      "probability": 0.219,
      "level": "MEDIUM",
      "prob_am": 0.248,
      "prob_pm": 0.193,
      "prob_night": 0.24,
      "level_am": "MEDIUM",
      "level_pm": "MEDIUM",
      "level_night": "HIGH",
      "hist_count": 1,
      "hist_score": 0.122,
      "top_cause": "쓰레기소각",
      "forest_danger_grade": 3
    },
    {
      "dong": "정문",
      "myeon": "양감",
      "lat": 37.02,
      "lng": 126.8775,
      "probability": 0.219,
      "level": "MEDIUM",
      "prob_am": 0.216,
      "prob_pm": 0.21,
      "prob_night": 0.246,
      "level_am": "MEDIUM",
      "level_pm": "MEDIUM",
      "level_night": "HIGH",
      "hist_count": 1,
      "hist_score": 0.171,
      "top_cause": "쓰레기소각",
      "forest_danger_grade": 3
    },
    {
      "dong": "목",
      "myeon": "",
      "lat": 37.1996,
      "lng": 126.8312,
      "probability": 0.217,
      "level": "MEDIUM",
      "prob_am": 0.221,
      "prob_pm": 0.216,
      "prob_night": 0.212,
      "level_am": "MEDIUM",
      "level_pm": "MEDIUM",
      "level_night": "MEDIUM",
      "hist_count": 2,
      "hist_score": 0.268,
      "top_cause": "입산자실화",
      "forest_danger_grade": 3
    },
    {
      "dong": "월문",
      "myeon": "팔탄",
      "lat": 37.0868,
      "lng": 126.8672,
      "probability": 0.217,
      "level": "MEDIUM",
      "prob_am": 0.231,
      "prob_pm": 0.202,
      "prob_night": 0.233,
      "level_am": "MEDIUM",
      "level_pm": "MEDIUM",
      "level_night": "HIGH",
      "hist_count": 1,
      "hist_score": 0.126,
      "top_cause": "입산자실화",
      "forest_danger_grade": 3
    },
    {
      "dong": "청오",
      "myeon": "비봉",
      "lat": 37.2492,
      "lng": 126.7995,
      "probability": 0.217,
      "level": "MEDIUM",
      "prob_am": 0.238,
      "prob_pm": 0.205,
      "prob_night": 0.217,
      "level_am": "MEDIUM",
      "level_pm": "MEDIUM",
      "level_night": "MEDIUM",
      "hist_count": 1,
      "hist_score": 0.122,
      "top_cause": "담뱃불실화",
      "forest_danger_grade": 3
    },
    {
      "dong": "화산",
      "myeon": "우정",
      "lat": 37.077,
      "lng": 126.6702,
      "probability": 0.217,
      "level": "MEDIUM",
      "prob_am": 0.237,
      "prob_pm": 0.207,
      "prob_night": 0.21,
      "level_am": "MEDIUM",
      "level_pm": "MEDIUM",
      "level_night": "MEDIUM",
      "hist_count": 1,
      "hist_score": 0.122,
      "top_cause": "입산자실화",
      "forest_danger_grade": 3
    },
    {
      "dong": "요당",
      "myeon": "양감",
      "lat": 37.0182,
      "lng": 126.8849,
      "probability": 0.216,
      "level": "MEDIUM",
      "prob_am": 0.244,
      "prob_pm": 0.194,
      "prob_night": 0.228,
      "level_am": "MEDIUM",
      "level_pm": "MEDIUM",
      "level_night": "HIGH",
      "hist_count": 1,
      "hist_score": 0.122,
      "top_cause": "담뱃불실화",
      "forest_danger_grade": 3
    },
    {
      "dong": "양노",
      "myeon": "비봉",
      "lat": 37.2363,
      "lng": 126.8045,
      "probability": 0.215,
      "level": "MEDIUM",
      "prob_am": 0.246,
      "prob_pm": 0.192,
      "prob_night": 0.227,
      "level_am": "MEDIUM",
      "level_pm": "MEDIUM",
      "level_night": "HIGH",
      "hist_count": 1,
      "hist_score": 0.122,
      "top_cause": "농산부산물소각",
      "forest_danger_grade": 3
    },
    {
      "dong": "어촌",
      "myeon": "매송",
      "lat": 37.1996,
      "lng": 126.8312,
      "probability": 0.215,
      "level": "MEDIUM",
      "prob_am": 0.244,
      "prob_pm": 0.193,
      "prob_night": 0.229,
      "level_am": "MEDIUM",
      "level_pm": "MEDIUM",
      "level_night": "HIGH",
      "hist_count": 1,
      "hist_score": 0.122,
      "top_cause": "농산부산물소각",
      "forest_danger_grade": 3
    },
    {
      "dong": "장지",
      "myeon": "",
      "lat": 37.1996,
      "lng": 126.8312,
      "probability": 0.213,
      "level": "MEDIUM",
      "prob_am": 0.211,
      "prob_pm": 0.204,
      "prob_night": 0.237,
      "level_am": "MEDIUM",
      "level_pm": "MEDIUM",
      "level_night": "HIGH",
      "hist_count": 1,
      "hist_score": 0.182,
      "top_cause": "입산자실화",
      "forest_danger_grade": 3
    },
    {
      "dong": "덕우",
      "myeon": "봉담",
      "lat": 37.2076,
      "lng": 126.9347,
      "probability": 0.212,
      "level": "MEDIUM",
      "prob_am": 0.246,
      "prob_pm": 0.187,
      "prob_night": 0.226,
      "level_am": "MEDIUM",
      "level_pm": "MEDIUM",
      "level_night": "MEDIUM",
      "hist_count": 1,
      "hist_score": 0.122,
      "top_cause": "쓰레기소각",
      "forest_danger_grade": 3
    },
    {
      "dong": "고포",
      "myeon": "성산",
      "lat": 37.1996,
      "lng": 126.8312,
      "probability": 0.211,
      "level": "MEDIUM",
      "prob_am": 0.229,
      "prob_pm": 0.192,
      "prob_night": 0.229,
      "level_am": "MEDIUM",
      "level_pm": "MEDIUM",
      "level_night": "HIGH",
      "hist_count": 1,
      "hist_score": 0.166,
      "top_cause": "쓰레기소각",
      "forest_danger_grade": 3
    },
    {
      "dong": "도이",
      "myeon": "향남",
      "lat": 37.0644,
      "lng": 126.82,
      "probability": 0.211,
      "level": "MEDIUM",
      "prob_am": 0.245,
      "prob_pm": 0.186,
      "prob_night": 0.223,
      "level_am": "MEDIUM",
      "level_pm": "MEDIUM",
      "level_night": "MEDIUM",
      "hist_count": 1,
      "hist_score": 0.122,
      "top_cause": "농산부산물소각",
      "forest_danger_grade": 3
    },
    {
      "dong": "종송",
      "myeon": "송산",
      "lat": 37.1839,
      "lng": 126.6861,
      "probability": 0.211,
      "level": "MEDIUM",
      "prob_am": 0.218,
      "prob_pm": 0.196,
      "prob_night": 0.238,
      "level_am": "MEDIUM",
      "level_pm": "MEDIUM",
      "level_night": "HIGH",
      "hist_count": 1,
      "hist_score": 0.135,
      "top_cause": "농산부산물소각",
      "forest_danger_grade": 3
    },
    {
      "dong": "칠곡",
      "myeon": "송산",
      "lat": 37.1983,
      "lng": 126.6812,
      "probability": 0.208,
      "level": "MEDIUM",
      "prob_am": 0.206,
      "prob_pm": 0.205,
      "prob_night": 0.218,
      "level_am": "MEDIUM",
      "level_pm": "MEDIUM",
      "level_night": "MEDIUM",
      "hist_count": 1,
      "hist_score": 0.166,
      "top_cause": "기타",
      "forest_danger_grade": 3
    },
    {
      "dong": "증거",
      "myeon": "향남",
      "lat": 37.0591,
      "lng": 126.8206,
      "probability": 0.203,
      "level": "MEDIUM",
      "prob_am": 0.198,
      "prob_pm": 0.196,
      "prob_night": 0.227,
      "level_am": "MEDIUM",
      "level_pm": "MEDIUM",
      "level_night": "HIGH",
      "hist_count": 1,
      "hist_score": 0.151,
      "top_cause": "입산자실화",
      "forest_danger_grade": 3
    },
    {
      "dong": "호곡",
      "myeon": "우정",
      "lat": 37.0576,
      "lng": 126.6896,
      "probability": 0.203,
      "level": "MEDIUM",
      "prob_am": 0.217,
      "prob_pm": 0.196,
      "prob_night": 0.199,
      "level_am": "MEDIUM",
      "level_pm": "MEDIUM",
      "level_night": "MEDIUM",
      "hist_count": 1,
      "hist_score": 0.125,
      "top_cause": "쓰레기소각",
      "forest_danger_grade": 3
    },
    {
      "dong": "지월",
      "myeon": "팔탄",
      "lat": 37.0863,
      "lng": 126.8682,
      "probability": 0.201,
      "level": "MEDIUM",
      "prob_am": 0.202,
      "prob_pm": 0.194,
      "prob_night": 0.216,
      "level_am": "MEDIUM",
      "level_pm": "MEDIUM",
      "level_night": "MEDIUM",
      "hist_count": 1,
      "hist_score": 0.135,
      "top_cause": "입산자실화",
      "forest_danger_grade": 3
    },
    {
      "dong": "청요리",
      "myeon": "비봉",
      "lat": 37.2526,
      "lng": 126.8139,
      "probability": 0.199,
      "level": "MEDIUM",
      "prob_am": 0.201,
      "prob_pm": 0.193,
      "prob_night": 0.211,
      "level_am": "MEDIUM",
      "level_pm": "MEDIUM",
      "level_night": "MEDIUM",
      "hist_count": 1,
      "hist_score": 0.135,
      "top_cause": "기타",
      "forest_danger_grade": 3
    },
    {
      "dong": "분천",
      "myeon": "봉담",
      "lat": 37.205,
      "lng": 126.9273,
      "probability": 0.198,
      "level": "MEDIUM",
      "prob_am": 0.217,
      "prob_pm": 0.183,
      "prob_night": 0.208,
      "level_am": "MEDIUM",
      "level_pm": "MEDIUM",
      "level_night": "MEDIUM",
      "hist_count": 1,
      "hist_score": 0.128,
      "top_cause": "쓰레기소각",
      "forest_danger_grade": 3
    },
    {
      "dong": "천천",
      "myeon": "매송",
      "lat": 37.1996,
      "lng": 126.8312,
      "probability": 0.198,
      "level": "MEDIUM",
      "prob_am": 0.205,
      "prob_pm": 0.192,
      "prob_night": 0.205,
      "level_am": "MEDIUM",
      "level_pm": "MEDIUM",
      "level_night": "MEDIUM",
      "hist_count": 1,
      "hist_score": 0.131,
      "top_cause": "입산자실화",
      "forest_danger_grade": 3
    },
    {
      "dong": "대양",
      "myeon": "양감",
      "lat": 37.0106,
      "lng": 126.874,
      "probability": 0.197,
      "level": "MEDIUM",
      "prob_am": 0.218,
      "prob_pm": 0.18,
      "prob_night": 0.209,
      "level_am": "MEDIUM",
      "level_pm": "LOW",
      "level_night": "MEDIUM",
      "hist_count": 1,
      "hist_score": 0.128,
      "top_cause": "기타",
      "forest_danger_grade": 3
    },
    {
      "dong": "송정",
      "myeon": "마도",
      "lat": 37.1224,
      "lng": 126.6993,
      "probability": 0.197,
      "level": "MEDIUM",
      "prob_am": 0.206,
      "prob_pm": 0.186,
      "prob_night": 0.211,
      "level_am": "MEDIUM",
      "level_pm": "MEDIUM",
      "level_night": "MEDIUM",
      "hist_count": 1,
      "hist_score": 0.166,
      "top_cause": "기타",
      "forest_danger_grade": 3
    },
    {
      "dong": "가재",
      "myeon": "팔탄",
      "lat": 37.1082,
      "lng": 126.8948,
      "probability": 0.196,
      "level": "MEDIUM",
      "prob_am": 0.213,
      "prob_pm": 0.184,
      "prob_night": 0.201,
      "level_am": "MEDIUM",
      "level_pm": "MEDIUM",
      "level_night": "MEDIUM",
      "hist_count": 1,
      "hist_score": 0.182,
      "top_cause": "기타",
      "forest_danger_grade": 3
    },
    {
      "dong": "어천",
      "myeon": "매송",
      "lat": 37.1996,
      "lng": 126.8312,
      "probability": 0.192,
      "level": "MEDIUM",
      "prob_am": 0.205,
      "prob_pm": 0.178,
      "prob_night": 0.207,
      "level_am": "MEDIUM",
      "level_pm": "LOW",
      "level_night": "MEDIUM",
      "hist_count": 1,
      "hist_score": 0.135,
      "top_cause": "쓰레기소각",
      "forest_danger_grade": 3
    },
    {
      "dong": "안석",
      "myeon": "남양",
      "lat": 37.2193,
      "lng": 126.7235,
      "probability": 0.191,
      "level": "MEDIUM",
      "prob_am": 0.206,
      "prob_pm": 0.178,
      "prob_night": 0.204,
      "level_am": "MEDIUM",
      "level_pm": "LOW",
      "level_night": "MEDIUM",
      "hist_count": 1,
      "hist_score": 0.135,
      "top_cause": "쓰레기소각",
      "forest_danger_grade": 3
    },
    {
      "dong": "천동",
      "myeon": "송산",
      "lat": 37.2003,
      "lng": 126.6781,
      "probability": 0.19,
      "level": "MEDIUM",
      "prob_am": 0.193,
      "prob_pm": 0.2,
      "prob_night": 0.162,
      "level_am": "MEDIUM",
      "level_pm": "MEDIUM",
      "level_night": "MEDIUM",
      "hist_count": 1,
      "hist_score": 0.259,
      "top_cause": "농산부산물소각",
      "forest_danger_grade": 3
    },
    {
      "dong": "영천",
      "myeon": "",
      "lat": 37.1996,
      "lng": 126.8312,
      "probability": 0.189,
      "level": "MEDIUM",
      "prob_am": 0.202,
      "prob_pm": 0.176,
      "prob_night": 0.206,
      "level_am": "MEDIUM",
      "level_pm": "LOW",
      "level_night": "MEDIUM",
      "hist_count": 1,
      "hist_score": 0.134,
      "top_cause": "입산자실화",
      "forest_danger_grade": 3
    },
    {
      "dong": "금당",
      "myeon": "마도",
      "lat": 37.1174,
      "lng": 126.6956,
      "probability": 0.187,
      "level": "MEDIUM",
      "prob_am": 0.207,
      "prob_pm": 0.176,
      "prob_night": 0.187,
      "level_am": "MEDIUM",
      "level_pm": "LOW",
      "level_night": "MEDIUM",
      "hist_count": 1,
      "hist_score": 0.197,
      "top_cause": "기타",
      "forest_danger_grade": 3
    },
    {
      "dong": "기안",
      "myeon": "",
      "lat": 37.1996,
      "lng": 126.8312,
      "probability": 0.186,
      "level": "MEDIUM",
      "prob_am": 0.207,
      "prob_pm": 0.176,
      "prob_night": 0.181,
      "level_am": "MEDIUM",
      "level_pm": "LOW",
      "level_night": "MEDIUM",
      "hist_count": 1,
      "hist_score": 0.197,
      "top_cause": "입산자실화",
      "forest_danger_grade": 3
    },
    {
      "dong": "복양",
      "myeon": "남양",
      "lat": 37.1928,
      "lng": 126.7134,
      "probability": 0.184,
      "level": "MEDIUM",
      "prob_am": 0.2,
      "prob_pm": 0.171,
      "prob_night": 0.192,
      "level_am": "MEDIUM",
      "level_pm": "LOW",
      "level_night": "MEDIUM",
      "hist_count": 1,
      "hist_score": 0.135,
      "top_cause": "건축물화재비화",
      "forest_danger_grade": 3
    },
    {
      "dong": "당하",
      "myeon": "봉담",
      "lat": 37.2203,
      "lng": 126.9364,
      "probability": 0.182,
      "level": "MEDIUM",
      "prob_am": 0.2,
      "prob_pm": 0.168,
      "prob_night": 0.191,
      "level_am": "MEDIUM",
      "level_pm": "LOW",
      "level_night": "MEDIUM",
      "hist_count": 1,
      "hist_score": 0.135,
      "top_cause": "담뱃불실화",
      "forest_danger_grade": 3
    },
    {
      "dong": "상",
      "myeon": "봉담",
      "lat": 37.2196,
      "lng": 126.9098,
      "probability": 0.182,
      "level": "MEDIUM",
      "prob_am": 0.194,
      "prob_pm": 0.171,
      "prob_night": 0.19,
      "level_am": "MEDIUM",
      "level_pm": "LOW",
      "level_night": "MEDIUM",
      "hist_count": 1,
      "hist_score": 0.151,
      "top_cause": "쓰레기소각",
      "forest_danger_grade": 3
    },
    {
      "dong": "독정",
      "myeon": "장안",
      "lat": 37.0626,
      "lng": 126.76,
      "probability": 0.178,
      "level": "MEDIUM",
      "prob_am": 0.194,
      "prob_pm": 0.165,
      "prob_night": 0.184,
      "level_am": "MEDIUM",
      "level_pm": "LOW",
      "level_night": "MEDIUM",
      "hist_count": 1,
      "hist_score": 0.151,
      "top_cause": "건축물화재비화",
      "forest_danger_grade": 3
    },
    {
      "dong": "수직",
      "myeon": "향남",
      "lat": 37.0637,
      "lng": 126.8198,
      "probability": 0.178,
      "level": "MEDIUM",
      "prob_am": 0.194,
      "prob_pm": 0.167,
      "prob_night": 0.183,
      "level_am": "MEDIUM",
      "level_pm": "LOW",
      "level_night": "MEDIUM",
      "hist_count": 1,
      "hist_score": 0.14,
      "top_cause": "담뱃불실화",
      "forest_danger_grade": 3
    },
    {
      "dong": "마산",
      "myeon": "송산",
      "lat": 37.1837,
      "lng": 126.7064,
      "probability": 0.177,
      "level": "MEDIUM",
      "prob_am": 0.194,
      "prob_pm": 0.162,
      "prob_night": 0.189,
      "level_am": "MEDIUM",
      "level_pm": "LOW",
      "level_night": "MEDIUM",
      "hist_count": 1,
      "hist_score": 0.149,
      "top_cause": "쓰레기소각",
      "forest_danger_grade": 3
    },
    {
      "dong": "북양",
      "myeon": "남양",
      "lat": 37.2153,
      "lng": 126.7384,
      "probability": 0.173,
      "level": "MEDIUM",
      "prob_am": 0.184,
      "prob_pm": 0.166,
      "prob_night": 0.172,
      "level_am": "MEDIUM",
      "level_pm": "LOW",
      "level_night": "MEDIUM",
      "hist_count": 1,
      "hist_score": 0.213,
      "top_cause": "쓰레기소각",
      "forest_danger_grade": 3
    }
  ]
}